[
  {
    "IDX": 1,
    "uniqueId": "CTL001",
    "BDONG_CD": "11",
    "CD_DIST_OBSV": "BRD001",
    "NM_DIST_OBSV": "서울 영등포 방송장비",
    "Auth": "admin",
    "userName": "관리자",
    "type": "broadcast",
    "dtmCreate": "2025-03-01T08:30:00Z",
    "RCMD": "PLAY",
    "Parm1": "긴급재난방송",
    "Parm2": "100",
    "BStatus": "완료",
    "RetData": "OK",
    "RetDate": "2025-03-01T08:30:05Z",
    "RegDate": "2025-03-01"
  },
  {
    "IDX": 2,
    "uniqueId": "CTL002",
    "BDONG_CD": "11",
    "CD_DIST_OBSV": "DSP001",
    "NM_DIST_OBSV": "서울 송파 전광판",
    "Auth": "admin",
    "userName": "관리자",
    "type": "display",
    "dtmCreate": "2025-03-01T08:35:00Z",
    "RCMD": "DISPLAY",
    "Parm1": "호우주의보 발령",
    "BStatus": "완료",
    "RetData": "OK",
    "RetDate": "2025-03-01T08:35:03Z",
    "RegDate": "2025-03-01"
  },
  {
    "IDX": 3,
    "uniqueId": "CTL003",
    "BDONG_CD": "11",
    "CD_DIST_OBSV": "GTE001",
    "NM_DIST_OBSV": "서울 노원 차단기",
    "Auth": "admin",
    "userName": "관리자",
    "type": "gate",
    "dtmCreate": "2025-03-01T08:40:00Z",
    "Gate": "CLOSE",
    "Light": "ON",
    "Sound": "ON",
    "GStatus": "완료",
    "RegDate": "2025-03-01"
  },
  {
    "IDX": 4,
    "uniqueId": "CTL004",
    "BDONG_CD": "26",
    "CD_DIST_OBSV": "BRD002",
    "NM_DIST_OBSV": "부산 동래 방송장비",
    "Auth": "user",
    "userName": "일반사용자",
    "type": "broadcast",
    "dtmCreate": "2025-03-01T09:00:00Z",
    "RCMD": "PLAY",
    "Parm1": "태풍 경보",
    "Parm2": "80",
    "BStatus": "완료",
    "RetData": "OK",
    "RetDate": "2025-03-01T09:00:04Z",
    "RegDate": "2025-03-01"
  },
  {
    "IDX": 5,
    "uniqueId": "CTL005",
    "BDONG_CD": "26",
    "CD_DIST_OBSV": "DSP002",
    "NM_DIST_OBSV": "부산 사하 전광판",
    "Auth": "user",
    "userName": "일반사용자",
    "type": "display",
    "dtmCreate": "2025-03-01T09:05:00Z",
    "RCMD": "DISPLAY",
    "Parm1": "침수 주의",
    "BStatus": "완료",
    "RetData": "OK",
    "RetDate": "2025-03-01T09:05:02Z",
    "RegDate": "2025-03-01"
  },
  {
    "IDX": 6,
    "uniqueId": "CTL006",
    "BDONG_CD": "26",
    "CD_DIST_OBSV": "GTE002",
    "NM_DIST_OBSV": "부산 금정 차단기",
    "Auth": "admin",
    "userName": "관리자",
    "type": "gate",
    "dtmCreate": "2025-03-01T09:10:00Z",
    "Gate": "OPEN",
    "Light": "OFF",
    "Sound": "OFF",
    "GStatus": "완료",
    "RegDate": "2025-03-01"
  },
  {
    "IDX": 7,
    "uniqueId": "CTL007",
    "BDONG_CD": "27",
    "CD_DIST_OBSV": "BRD003",
    "NM_DIST_OBSV": "대구 북구 방송장비",
    "Auth": "admin",
    "userName": "관리자",
    "type": "broadcast",
    "dtmCreate": "2025-02-28T14:00:00Z",
    "RCMD": "PLAY",
    "Parm1": "폭염 경보",
    "Parm2": "90",
    "BStatus": "완료",
    "RetData": "OK",
    "RetDate": "2025-02-28T14:00:06Z",
    "RegDate": "2025-02-28"
  },
  {
    "IDX": 8,
    "uniqueId": "CTL008",
    "BDONG_CD": "28",
    "CD_DIST_OBSV": "DSP004",
    "NM_DIST_OBSV": "인천 부평 전광판",
    "Auth": "manager",
    "userName": "매니저",
    "type": "display",
    "dtmCreate": "2025-02-28T14:30:00Z",
    "RCMD": "DISPLAY",
    "Parm1": "대설 주의보",
    "BStatus": "완료",
    "RetData": "OK",
    "RetDate": "2025-02-28T14:30:03Z",
    "RegDate": "2025-02-28"
  },
  {
    "IDX": 9,
    "uniqueId": "CTL009",
    "BDONG_CD": "28",
    "CD_DIST_OBSV": "GTE003",
    "NM_DIST_OBSV": "인천 서구 차단기",
    "Auth": "admin",
    "userName": "관리자",
    "type": "gate",
    "dtmCreate": "2025-02-28T15:00:00Z",
    "Gate": "CLOSE",
    "Light": "ON",
    "Sound": "ON",
    "GStatus": "완료",
    "RegDate": "2025-02-28"
  },
  {
    "IDX": 10,
    "uniqueId": "CTL010",
    "BDONG_CD": "30",
    "CD_DIST_OBSV": "BRD004",
    "NM_DIST_OBSV": "대전 동구 방송장비",
    "Auth": "user",
    "userName": "일반사용자",
    "type": "broadcast",
    "dtmCreate": "2025-02-28T16:00:00Z",
    "RCMD": "STOP",
    "Parm1": "방송 중지",
    "BStatus": "완료",
    "RetData": "OK",
    "RetDate": "2025-02-28T16:00:02Z",
    "RegDate": "2025-02-28"
  },
  {
    "IDX": 11,
    "uniqueId": "CTL011",
    "BDONG_CD": "41",
    "CD_DIST_OBSV": "BRD005",
    "NM_DIST_OBSV": "경기 안산 방송장비",
    "Auth": "admin",
    "userName": "관리자",
    "type": "broadcast",
    "dtmCreate": "2025-02-27T10:00:00Z",
    "RCMD": "PLAY",
    "Parm1": "홍수 경보",
    "Parm2": "100",
    "BStatus": "완료",
    "RetData": "OK",
    "RetDate": "2025-02-27T10:00:05Z",
    "RegDate": "2025-02-27"
  },
  {
    "IDX": 12,
    "uniqueId": "CTL012",
    "BDONG_CD": "41",
    "CD_DIST_OBSV": "DSP007",
    "NM_DIST_OBSV": "경기 용인 전광판",
    "Auth": "admin",
    "userName": "관리자",
    "type": "display",
    "dtmCreate": "2025-02-27T10:30:00Z",
    "RCMD": "DISPLAY",
    "Parm1": "산사태 주의",
    "BStatus": "완료",
    "RetData": "OK",
    "RetDate": "2025-02-27T10:30:04Z",
    "RegDate": "2025-02-27"
  },
  {
    "IDX": 13,
    "uniqueId": "CTL013",
    "BDONG_CD": "41",
    "CD_DIST_OBSV": "GTE004",
    "NM_DIST_OBSV": "경기 파주 차단기",
    "Auth": "admin",
    "userName": "관리자",
    "type": "gate",
    "dtmCreate": "2025-02-27T11:00:00Z",
    "Gate": "CLOSE",
    "Light": "ON",
    "Sound": "ON",
    "GStatus": "실패",
    "RegDate": "2025-02-27"
  },
  {
    "IDX": 14,
    "uniqueId": "CTL014",
    "BDONG_CD": "42",
    "CD_DIST_OBSV": "BRD006",
    "NM_DIST_OBSV": "강원 태백 방송장비",
    "Auth": "manager",
    "userName": "매니저",
    "type": "broadcast",
    "dtmCreate": "2025-02-26T09:00:00Z",
    "RCMD": "PLAY",
    "Parm1": "강풍 경보",
    "Parm2": "85",
    "BStatus": "완료",
    "RetData": "OK",
    "RetDate": "2025-02-26T09:00:03Z",
    "RegDate": "2025-02-26"
  },
  {
    "IDX": 15,
    "uniqueId": "CTL015",
    "BDONG_CD": "42",
    "CD_DIST_OBSV": "DSP008",
    "NM_DIST_OBSV": "강원 속초 전광판",
    "Auth": "admin",
    "userName": "관리자",
    "type": "display",
    "dtmCreate": "2025-02-26T09:30:00Z",
    "RCMD": "DISPLAY",
    "Parm1": "풍랑 주의보",
    "BStatus": "완료",
    "RetData": "OK",
    "RetDate": "2025-02-26T09:30:02Z",
    "RegDate": "2025-02-26"
  },
  {
    "IDX": 16,
    "uniqueId": "CTL016",
    "BDONG_CD": "43",
    "CD_DIST_OBSV": "GTE005",
    "NM_DIST_OBSV": "충북 옥천 차단기",
    "Auth": "admin",
    "userName": "관리자",
    "type": "gate",
    "dtmCreate": "2025-02-25T14:00:00Z",
    "Gate": "OPEN",
    "Light": "OFF",
    "Sound": "OFF",
    "GStatus": "완료",
    "RegDate": "2025-02-25"
  },
  {
    "IDX": 17,
    "uniqueId": "CTL017",
    "BDONG_CD": "44",
    "CD_DIST_OBSV": "BRD007",
    "NM_DIST_OBSV": "충남 논산 방송장비",
    "Auth": "user",
    "userName": "일반사용자",
    "type": "broadcast",
    "dtmCreate": "2025-02-25T15:00:00Z",
    "RCMD": "PLAY",
    "Parm1": "지진 경보",
    "Parm2": "100",
    "BStatus": "완료",
    "RetData": "OK",
    "RetDate": "2025-02-25T15:00:07Z",
    "RegDate": "2025-02-25"
  },
  {
    "IDX": 18,
    "uniqueId": "CTL018",
    "BDONG_CD": "44",
    "CD_DIST_OBSV": "DSP010",
    "NM_DIST_OBSV": "충남 서산 전광판",
    "Auth": "admin",
    "userName": "관리자",
    "type": "display",
    "dtmCreate": "2025-02-24T08:00:00Z",
    "RCMD": "DISPLAY",
    "Parm1": "한파 경보",
    "BStatus": "완료",
    "RetData": "OK",
    "RetDate": "2025-02-24T08:00:03Z",
    "RegDate": "2025-02-24"
  },
  {
    "IDX": 19,
    "uniqueId": "CTL019",
    "BDONG_CD": "45",
    "CD_DIST_OBSV": "GTE006",
    "NM_DIST_OBSV": "전북 남원 차단기",
    "Auth": "admin",
    "userName": "관리자",
    "type": "gate",
    "dtmCreate": "2025-02-24T09:00:00Z",
    "Gate": "CLOSE",
    "Light": "ON",
    "Sound": "ON",
    "GStatus": "완료",
    "RegDate": "2025-02-24"
  },
  {
    "IDX": 20,
    "uniqueId": "CTL020",
    "BDONG_CD": "46",
    "CD_DIST_OBSV": "BRD008",
    "NM_DIST_OBSV": "전남 나주 방송장비",
    "Auth": "admin",
    "userName": "관리자",
    "type": "broadcast",
    "dtmCreate": "2025-02-23T11:00:00Z",
    "RCMD": "PLAY",
    "Parm1": "호우 경보",
    "Parm2": "95",
    "BStatus": "완료",
    "RetData": "OK",
    "RetDate": "2025-02-23T11:00:04Z",
    "RegDate": "2025-02-23"
  }
]
